{
    "5": {
        "sirius_mapping": "SPOUSE"
    },
    "10": {
        "sirius_mapping": "SPOUSE"
    },
    "11": {
        "sirius_mapping": "CHILD"
    },
    "12": {
        "sirius_mapping": "PARENT"
    },
    "13": {
        "sirius_mapping": "CIVIL"
    },
    "19": {
        "sirius_mapping": "OTHERRELATION"
    },
    "20": {
        "sirius_mapping": "BANK"
    },
    "21": {
        "sirius_mapping": "SOLICITOR"
    },
    "22": {
        "sirius_mapping": "ACCOUNTANT"
    },
    "90": {
        "sirius_mapping": "SPOUSE"
    },
    "29": {
        "sirius_mapping": "OTHERPROFESSIONAL"
    },
    "14": {
        "sirius_mapping": "FRIEND"
    },
    "15": {
        "sirius_mapping": "PARTNER"
    },
    "63": {
        "sirius_mapping": "PANEL"
    },
    "7": {
        "sirius_mapping": "SIBLING"
    },
    "24": {
        "sirius_mapping": "UNREGULATED"
    },
    "25": {
        "sirius_mapping": "LEGAL"
    }
}