{
    "worksheets": {
        "client_death_notifications": {
            "total_rows": 9,
            "total_unmapped": 1,
            "total_mapped": 8,
            "percentage_complete": 89
        },
        "deputy_death_notifications": {
            "total_rows": 9,
            "total_unmapped": 0,
            "total_mapped": 9,
            "percentage_complete": 100
        },
        "client_violent_warnings": {
            "total_rows": 8,
            "total_unmapped": 5,
            "total_mapped": 3,
            "percentage_complete": 38
        },
        "deputy_violent_warnings": {
            "total_rows": 8,
            "total_unmapped": 5,
            "total_mapped": 3,
            "percentage_complete": 38
        },
        "client_special_warnings": {
            "total_rows": 8,
            "total_unmapped": 5,
            "total_mapped": 3,
            "percentage_complete": 38
        },
        "deputy_special_warnings": {
            "total_rows": 8,
            "total_unmapped": 5,
            "total_mapped": 3,
            "percentage_complete": 38
        },
        "client_saarcheck_warnings": {
            "total_rows": 8,
            "total_unmapped": 5,
            "total_mapped": 3,
            "percentage_complete": 38
        },
        "client_nodebtchase_warnings": {
            "total_rows": 8,
            "total_unmapped": 5,
            "total_mapped": 3,
            "percentage_complete": 38
        },
        "person_warning": {
            "total_rows": 2,
            "total_unmapped": 0,
            "total_mapped": 2,
            "percentage_complete": 100
        },
        "cases": {
            "total_rows": 58,
            "total_unmapped": 5,
            "total_mapped": 53,
            "percentage_complete": 91
        },
        "person_caseitem": {
            "total_rows": 2,
            "total_unmapped": 0,
            "total_mapped": 2,
            "percentage_complete": 100
        },
        "visits": {
            "total_rows": 18,
            "total_unmapped": 9,
            "total_mapped": 9,
            "percentage_complete": 50
        },
        "visitor": {
            "total_rows": 2,
            "total_unmapped": 1,
            "total_mapped": 1,
            "percentage_complete": 50
        },
        "client_persons": {
            "total_rows": 34,
            "total_unmapped": 4,
            "total_mapped": 30,
            "percentage_complete": 88
        },
        "client_phonenumbers": {
            "total_rows": 6,
            "total_unmapped": 0,
            "total_mapped": 6,
            "percentage_complete": 100
        }
    },
    "total": {
        "worksheets": {
            "total_sheets": 17,
            "total_complete": 1
        },
        "fields": {
            "total_fields": 208,
            "total_unmapped": 60,
            "total_mapped": 148,
            "percentage_complete": 71
        }
    }
}